digitalarticle/__init__.py
digitalarticle/_version.py
digitalarticle/backend.py
digitalarticle/frontend.py
digitalarticle/py.typed
digitalarticle-0.1.5.dist-info/METADATA
digitalarticle-0.1.5.dist-info/WHEEL
digitalarticle-0.1.5.dist-info/entry_points.txt
digitalarticle-0.1.5.dist-info/top_level.txt
digitalarticle-0.1.5.dist-info/RECORD
