Metadata-Version: 2.4
Name: DigitalArticle
Version: 0.1.5
Summary: Command-line tools for Digital Article notebook application
Author-email: Laurent-Philippe Albou <contact@abstractcore.ai>
Maintainer-email: Laurent-Philippe Albou <contact@abstractcore.ai>
Project-URL: Homepage, https://github.com/lpalbou/digitalarticle
Project-URL: Documentation, https://github.com/lpalbou/digitalarticle
Project-URL: Repository, https://github.com/lpalbou/digitalarticle.git
Project-URL: Bug Tracker, https://github.com/lpalbou/digitalarticle/issues
Keywords: notebook,data-analysis,bioinformatics,jupyter,cli
Classifier: Development Status :: 4 - Beta
Classifier: Intended Audience :: Developers
Classifier: Intended Audience :: Science/Research
Classifier: Operating System :: OS Independent
Classifier: Programming Language :: Python :: 3
Classifier: Programming Language :: Python :: 3.8
Classifier: Programming Language :: Python :: 3.9
Classifier: Programming Language :: Python :: 3.10
Classifier: Programming Language :: Python :: 3.11
Classifier: Programming Language :: Python :: 3.12
Classifier: Programming Language :: Python :: 3.13
Classifier: Topic :: Scientific/Engineering
Classifier: Topic :: Software Development :: Libraries :: Python Modules
Requires-Python: >=3.8
Requires-Dist: fastapi>=0.104.1
Requires-Dist: uvicorn[standard]>=0.24.0
Requires-Dist: abstractcore[all]>=2.4.5
Requires-Dist: pandas>=2.1.4
Requires-Dist: numpy>=1.26.0
Requires-Dist: matplotlib>=3.8.2
Requires-Dist: plotly>=5.17.0
Requires-Dist: seaborn>=0.13.0
Requires-Dist: scikit-learn>=1.3.2
Requires-Dist: scipy>=1.11.4
Requires-Dist: jupyter>=1.0.0
Requires-Dist: pillow>=10.1.0
Requires-Dist: pydantic>=2.5.2
Requires-Dist: python-multipart>=0.0.6
Requires-Dist: reportlab>=4.0.7
Requires-Dist: weasyprint>=60.0
Requires-Dist: markdown>=3.5.1
Provides-Extra: dev
Requires-Dist: pytest>=7.0.0; extra == "dev"
Requires-Dist: black>=22.0.0; extra == "dev"
Requires-Dist: flake8>=4.0.0; extra == "dev"
Requires-Dist: mypy>=1.0.0; extra == "dev"
Provides-Extra: all
Requires-Dist: fastapi>=0.104.1; extra == "all"
Requires-Dist: uvicorn[standard]>=0.24.0; extra == "all"
Requires-Dist: abstractcore[all]>=2.4.5; extra == "all"
Requires-Dist: pandas>=2.1.4; extra == "all"
Requires-Dist: numpy>=1.26.0; extra == "all"
Requires-Dist: matplotlib>=3.8.2; extra == "all"
Requires-Dist: plotly>=5.17.0; extra == "all"
Requires-Dist: seaborn>=0.13.0; extra == "all"
Requires-Dist: scikit-learn>=1.3.2; extra == "all"
Requires-Dist: scipy>=1.11.4; extra == "all"
Requires-Dist: jupyter>=1.0.0; extra == "all"
Requires-Dist: pillow>=10.1.0; extra == "all"
Requires-Dist: pydantic>=2.5.2; extra == "all"
Requires-Dist: python-multipart>=0.0.6; extra == "all"
Requires-Dist: reportlab>=4.0.7; extra == "all"
Requires-Dist: weasyprint>=60.0; extra == "all"
Requires-Dist: markdown>=3.5.1; extra == "all"
